.gitignore
README.rst
runtests.py
setup.py
django_object_permission.egg-info/PKG-INFO
django_object_permission.egg-info/SOURCES.txt
django_object_permission.egg-info/dependency_links.txt
django_object_permission.egg-info/not-zip-safe
django_object_permission.egg-info/requires.txt
django_object_permission.egg-info/top_level.txt
object_permission/__init__.py
object_permission/admin.py
object_permission/backends.py
object_permission/decorators.py
object_permission/mediators.py
object_permission/models.py
object_permission/sites.py
object_permission/utils.py
object_permission/handlers/__init__.py
object_permission/handlers/authenticated.py
object_permission/handlers/author.py
object_permission/handlers/base.py
object_permission/management/commands/remodify_object_permission.py
object_permission/templatetags/__init__.py
object_permission/templatetags/object_permission_tags.py
object_permission/tests/__init__.py
object_permission/tests/override_settings.py
object_permission/tests/test_models.py
object_permission/tests/testapp/__init__.py
object_permission/tests/testapp/models.py
object_permission/tests/testapp/ophandler.py
object_permission/tests/testapp/fixtures/object_permission_test.yaml
tests/database.db
tests/src/miniblog/__init__.py
tests/src/miniblog/manage.py
tests/src/miniblog/settings.py
tests/src/miniblog/urls.py
tests/src/miniblog/autocmds/__init__.py
tests/src/miniblog/blogs/__init__.py
tests/src/miniblog/blogs/forms.py
tests/src/miniblog/blogs/models.py
tests/src/miniblog/blogs/ophandler.py
tests/src/miniblog/blogs/urls.py
tests/src/miniblog/blogs/views.py
tests/src/miniblog/blogs/fixtures/test.yaml
tests/src/miniblog/blogs/templates/404.html
tests/src/miniblog/blogs/templates/blog/entry_confirm_delete.html
tests/src/miniblog/blogs/templates/blog/entry_detail.html
tests/src/miniblog/blogs/templates/blog/entry_form.html
tests/src/miniblog/blogs/templates/blog/entry_list.html
tests/src/miniblog/blogs/tests/__init__.py
tests/src/miniblog/blogs/tests/test_models.py
tests/src/miniblog/blogs/tests/test_views.py
tests/static/css/style.css
tests/static/css/style.scss
tests/static/css/image/edit.png
tests/static/css/image/trash.png
tests/templates/404.html
tests/templates/base.html
tests/templates/blogs/entry_confirm_delete.html
