Metadata-Version: 1.0
Name: django-object-permission
Version: 0.5.1
Summary: Add object specific permission for particualr User/Group, All authenticated user or Anonymous user
Home-page: https://github.com/lambdalisue/django-object-permission
Author: Alisue
Author-email: lambdalisue@hashnote.net
License: MIT
Download-URL: https://github.com/lambdalisue/django-object-permission/tarball/master
Keywords: django permission object
Platform: UNKNOWN
Classifier: Framework :: Django
Classifier: Intended Audience :: Developers
Classifier: License :: OSI Approved :: MIT License
Classifier: Programming Language :: Python
Classifier: Topic :: Internet :: WWW/HTTP
